sorted_months_weekdays/__init__.py
sorted_months_weekdays/maincode.py
sorted_months_weekdays-0.1.dist-info/DESCRIPTION.rst
sorted_months_weekdays-0.1.dist-info/METADATA
sorted_months_weekdays-0.1.dist-info/RECORD
sorted_months_weekdays-0.1.dist-info/WHEEL
sorted_months_weekdays-0.1.dist-info/metadata.json
sorted_months_weekdays-0.1.dist-info/top_level.txt
