Metadata-Version: 2.0
Name: sorted-months-weekdays
Version: 0.1
Summary: Get sorted Months and Weeks by chronological order
Home-page: UNKNOWN
Author: Yeddu Dinesh Babu
Author-email: ydineshy225@gmail.com
License: UNKNOWN
Platform: UNKNOWN
